lotery_drawer/__init__.py
lotery_drawer/drawer.py
lotery_drawer/tools.py
lotery_drawer-1.0.1.dist-info/LICENSE
lotery_drawer-1.0.1.dist-info/METADATA
lotery_drawer-1.0.1.dist-info/WHEEL
lotery_drawer-1.0.1.dist-info/top_level.txt
lotery_drawer-1.0.1.dist-info/RECORD
