Metadata-Version: 2.1
Name: lotery-drawer
Version: 1.0.1
Summary: A simple, proven and non-falsifiable lottery draw tool
Home-page: https://github.com/crypt-online/lotery-drawer
Author: Crypt Online
Author-email: admin@hxrobot.io
License: UNKNOWN
Platform: UNKNOWN
Classifier: Programming Language :: Python :: 3
Classifier: License :: OSI Approved :: GNU General Public License v3 (GPLv3)
Classifier: Operating System :: OS Independent
Requires-Python: >=3.6
